.gitignore
LICENSE
README.md
setup.cfg
setup.py
examples/__init__.py
examples/resale_hdb.py
merlion/__init__.py
merlion/merlion.py
merlion.egg-info/PKG-INFO
merlion.egg-info/SOURCES.txt
merlion.egg-info/dependency_links.txt
merlion.egg-info/not-zip-safe
merlion.egg-info/requires.txt
merlion.egg-info/top_level.txt