Metadata-Version: 1.1
Name: merlion
Version: 0.1
Summary: Machine Learning Package
Home-page: https://github.com/thufirtan/merlion
Author: KC Tan
Author-email: kctan6@gmail.com
License: MIT
Download-URL: https://github.com/thufirtan/merlion/archive/v0.1.tar.gz
Platform: UNKNOWN
